{
  "sayasaya": {
   "password": "$2y$12$zypycousOOnuShoIZTqOmufKmaSwRX/n6pS0USMU0VODukOZfRZae",
   "devices": ["REDMINOTE9PRO5C1031A7B688B47A","REDMINOTE9PRODC742EDE4C30EE59"],
   "expiry": "31-10-2024 12:00 PM"
 },
  "ibnu2612": {
   "password": "$2y$12$L4jwkgliXpq445CZqvlASuIYuyBETwDkyE3ccSbZYJnPMu61CR.ey",
   "devices": ["SM-J730GE3479373F1791A9F","M2010J19CG36AF9F55745012EE"],
   "expiry": "26-12-2023 12:00 PM"
},
  "derry0112": {
   "password": "$2y$12$wDth7DcrfDNGeJQW.lNsQOnf/Kq21XaF7hGH4sNFAVXnl/8E57edu",
   "devices": ["SM-A507FNA2E6771A9762A651"],
   "expiry": "01-12-2023 12:00 PM"
 },
  "gopartner1501": {
   "password": "$2y$12$hF8Uvuqu6bZBvDH6iTho7.kUu/eWVWzjbrmaxxhLkNRDw7S1a.cvy",
   "devices": ["SM-A042FC74622F854E3D6DB","VIVO1802IBQG4LCEWOFM49CY","M2006C3MGDD05DCDD7FEA3C27","INFINIXX653C13ED21DC40D073D9","SM-A346EAC4AA2E5ED78F967","SM-A105G6BCEF25F216C4BD8","REDMINOTE8EBD9B61DFA0D9BFD","CPH20838E4A4FE8EFBF0B84","SM-A105G7749A9C451AB8A51","M2006C3MG318CA16088118014","MI82579C045707622CD"],
   "expiry": "31-10-2024 12:00 PM"
 },
  "dgk565656": {
   "password": "$2y$12$4TNzq4idvI8VKgJilJ//R.gpoZpijmchs3x4awCvvcd9qfc/9e13e",
   "devices": ["REDMI4X4CD05E4D7D04"],
   "expiry": "07-12-2023 12:00 PM"
 },
  "kaysar3434": {
   "password": "$2y$12$EqL93XGKQpNza5PmYqutu.WNfH57AEEYzXPlDUnZKOg.wtoAF1roS",
   "devices": ["M2101K6G1E21811675FDA2CD"],
   "expiry": "02-12-2023 12:00 PM"
 },
}
